{"nodes":{"node:14":{"location":{"x":-3032,"y":-214}},"node:16":{"location":{"x":-2664,"y":-218}},"node:22":{"location":{"x":-2638,"y":-51}},"node:30":{"location":{"x":-2280,"y":-224}},"node:34":{"location":{"x":-1896,"y":-224}},"node:38":{"location":{"x":-648,"y":-410}},"node:4":{"location":{"x":-264,"y":-372}},"node:50":{"location":{"x":-2638,"y":-323}},"node:52":{"location":{"x":-2280,"y":-640}},"node:56":{"location":{"x":-2280,"y":-420}},"node:64":{"location":{"x":-1592,"y":-224}},"node:67":{"location":{"x":-1896,"y":-640}},"node:70":{"location":{"x":-1896,"y":-416}},"node:80":{"location":{"x":-1566,"y":-51}},"node:85":{"location":{"x":-1288,"y":-224}},"node:89":{"location":{"x":-984,"y":-224}}},"selection":null,"view":{"scroll":{"x":-2624.36328125,"y":-632.32757568359375},"visible_rect":{"max":{"x":-1428.484375,"y":514.22991943359375},"min":{"x":-3499.151123046875,"y":-843.10345458984375}},"zoom":0.75}}